{
  "_class": "symbolInstance",
  "booleanOperation": -1,
  "clippingMaskMode": 0,
  "do_objectID": "F3D91A00-4B4D-45FB-8652-BFC12AA17474",
  "exportOptions": {
    "_class": "exportOptions",
    "do_objectID": "C1D10AF9-6A3D-4446-89A6-A3AE85B2B2B7",
    "exportFormats": [
    ],
    "includedLayerIds": [
    ],
    "layerOptions": 0,
    "shouldTrim": false
  },
  "frame": {
    "_class": "rect",
    "constrainProportions": false,
    "do_objectID": "908614A7-F262-4EC5-81B0-F0AF49F41D9E",
    "height": 88,
    "width": 315,
    "x": 674,
    "y": 2104
  },
  "hasClippingMask": false,
  "horizontalSpacing": 0,
  "isFixedToViewport": false,
  "isFlippedHorizontal": false,
  "isFlippedVertical": false,
  "isLocked": false,
  "isVisible": true,
  "layerListExpandedType": 0,
  "name": "Atom/ Button Copy",
  "nameIsFixed": false,
  "overrideValues": [
    {
      "_class": "overrideValue",
      "do_objectID": "924631C2-FA13-40D6-867E-A42B14167F6A",
      "overrideName": "ACC2B278-9BB8-414C-AF8D-15D7E3B53E0F_stringValue",
      "value": "VIEW GALLERY"
    }
  ],
  "resizingConstraint": 63,
  "resizingType": 0,
  "rotation": 0,
  "scale": 1,
  "shouldBreakMaskChain": false,
  "style": {
    "_class": "style",
    "do_objectID": "59151E64-D64F-4FB9-AAF7-62B6E1C5E399",
    "endMarkerType": 0,
    "miterLimit": 10,
    "startMarkerType": 0,
    "windingRule": 1
  },
  "symbolID": "8AA0C15D-CD34-4D28-B4FF-3AD600911BB5",
  "verticalSpacing": 0
}