{
  "_class": "shapePath",
  "booleanOperation": -1,
  "clippingMaskMode": 0,
  "do_objectID": "2349566A-1B2C-4F7B-9A91-659157F5093E",
  "edited": true,
  "exportOptions": {
    "_class": "exportOptions",
    "do_objectID": "BAC40499-EA29-4822-ACC6-25E238B1437B",
    "exportFormats": [
    ],
    "includedLayerIds": [
    ],
    "layerOptions": 0,
    "shouldTrim": false
  },
  "frame": {
    "_class": "rect",
    "constrainProportions": false,
    "do_objectID": "07EC7C61-FD6F-4D2F-AEB3-A3359959B289",
    "height": 1,
    "width": 1019,
    "x": 210,
    "y": 1452
  },
  "hasClippingMask": false,
  "isClosed": false,
  "isFixedToViewport": false,
  "isFlippedHorizontal": false,
  "isFlippedVertical": false,
  "isLocked": false,
  "isVisible": true,
  "layerListExpandedType": 0,
  "name": "Line",
  "nameIsFixed": false,
  "pointRadiusBehaviour": 1,
  "points": [
    {
      "_class": "curvePoint",
      "cornerRadius": 0,
      "curveFrom": "{0.0078508341511285655, 0.50000000000000011}",
      "curveMode": 1,
      "curveTo": "{0.0078508341511285655, 0.50000000000000011}",
      "hasCurveFrom": false,
      "hasCurveTo": false,
      "point": "{0.00098135426889101041, 0.5}"
    },
    {
      "_class": "curvePoint",
      "cornerRadius": 0,
      "curveFrom": "{0.0078508341511285655, 0.50000000000000011}",
      "curveMode": 1,
      "curveTo": "{0.0078508341511285655, 0.50000000000000011}",
      "hasCurveFrom": false,
      "hasCurveTo": false,
      "point": "{1, 0.50000000000000011}"
    }
  ],
  "resizingConstraint": 63,
  "resizingType": 0,
  "rotation": 0,
  "shouldBreakMaskChain": false,
  "style": {
    "_class": "style",
    "borderOptions": {
      "_class": "borderOptions",
      "dashPattern": [
      ],
      "do_objectID": "73EC603E-143C-4845-AF58-68A8A222BDE6",
      "isEnabled": false,
      "lineCapStyle": 2,
      "lineJoinStyle": 0
    },
    "borders": [
      {
        "_class": "border",
        "color": {
          "_class": "color",
          "alpha": 1,
          "blue": 0.2902374565601349,
          "green": 0.2901752889156342,
          "red": 0.290221631526947
        },
        "fillType": 0,
        "isEnabled": true,
        "position": 0,
        "thickness": 1
      }
    ],
    "do_objectID": "27FD932E-54A0-4086-BDBC-CF820E1BEB60",
    "endMarkerType": 0,
    "fills": [
      {
        "_class": "fill",
        "color": {
          "_class": "color",
          "alpha": 1,
          "blue": 0.847,
          "green": 0.847,
          "red": 0.847
        },
        "fillType": 0,
        "isEnabled": false,
        "noiseIndex": 0,
        "noiseIntensity": 0,
        "patternFillType": 1,
        "patternTileScale": 1
      }
    ],
    "miterLimit": 10,
    "startMarkerType": 0,
    "windingRule": 1
  }
}